cli.py
app/__init__.py
app/main.py
app/api/__init__.py
app/api/endpoints/__init__.py
app/api/endpoints/image_processing.py
app/core/__init__.py
app/core/config.py
app/core/firebase_setup.py
app/core/state.py
app/models/__init__.py
app/models/image.py
app/services/__init__.py
app/utils/__init__.py
app/utils/ai_handler.py
app/utils/file_utils.py
app/utils/gcs_utils.py
app/utils/image_processor.py
image_filename_ai-0.1.0.dist-info/licenses/LICENSE
image_filename_ai-0.1.0.dist-info/METADATA
image_filename_ai-0.1.0.dist-info/WHEEL
image_filename_ai-0.1.0.dist-info/entry_points.txt
image_filename_ai-0.1.0.dist-info/top_level.txt
image_filename_ai-0.1.0.dist-info/RECORD
