Metadata-Version: 2.4
Name: image-filename-ai
Version: 0.1.0
Summary: AI-powered image filename generator using Google Gemini - Transform generic image files into descriptive, SEO-friendly names
Author-email: Matija Ziberna <matijazib@gmail.com>
Maintainer-email: Matija Ziberna <matijazib@gmail.com>
License-Expression: MIT
Project-URL: Homepage, https://github.com/matija2209/image-filename-ai
Project-URL: Repository, https://github.com/matija2209/image-filename-ai
Project-URL: Issues, https://github.com/matija2209/image-filename-ai/issues
Project-URL: Documentation, https://github.com/matija2209/image-filename-ai#readme
Keywords: ai,image,filename,gemini,google-cloud,cli,batch-processing,seo,automation,computer-vision,machine-learning
Classifier: Development Status :: 4 - Beta
Classifier: Environment :: Console
Classifier: Intended Audience :: Developers
Classifier: Intended Audience :: End Users/Desktop
Classifier: Operating System :: OS Independent
Classifier: Programming Language :: Python :: 3
Classifier: Programming Language :: Python :: 3.11
Classifier: Programming Language :: Python :: 3.12
Classifier: Programming Language :: Python :: 3.13
Classifier: Topic :: Multimedia :: Graphics
Classifier: Topic :: Software Development :: Libraries :: Python Modules
Classifier: Topic :: Utilities
Classifier: Topic :: Internet :: WWW/HTTP :: Dynamic Content
Requires-Python: >=3.11
License-File: LICENSE
Requires-Dist: google-cloud-aiplatform>=1.71.0
Requires-Dist: vertexai>=1.71.0
Requires-Dist: python-dotenv>=1.1.0
Requires-Dist: Pillow>=10.0.0
Provides-Extra: api
Requires-Dist: fastapi>=0.115.0; extra == "api"
Requires-Dist: uvicorn>=0.34.0; extra == "api"
Requires-Dist: firebase-admin>=6.5.0; extra == "api"
Requires-Dist: google-cloud-storage>=2.19.0; extra == "api"
Requires-Dist: google-cloud-firestore>=2.20.0; extra == "api"
Provides-Extra: dev
Requires-Dist: black>=24.0.0; extra == "dev"
Requires-Dist: ruff>=0.1.0; extra == "dev"
Requires-Dist: pytest>=8.0.0; extra == "dev"
Requires-Dist: pytest-mock>=3.14.0; extra == "dev"
Dynamic: license-file
